lkj/__init__.py
lkj/chunking.py
lkj/dicts.py
lkj/filesys.py
lkj/funcs.py
lkj/importing.py
lkj/iterables.py
lkj/loggers.py
lkj/misc.py
lkj/strings.py
lkj/tests/__init__.py
lkj/tests/test_strings.py
lkj-0.1.48.dist-info/licenses/LICENSE
lkj-0.1.48.dist-info/METADATA
lkj-0.1.48.dist-info/WHEEL
lkj-0.1.48.dist-info/top_level.txt
lkj-0.1.48.dist-info/RECORD
