Metadata-Version: 2.4
Name: lkj
Version: 0.1.48
Summary: A dump of homeless useful utils
Home-page: https://github.com/thorwhalen/lkj
Author: Thor Whalen
License: apache-2.0
Platform: any
License-File: LICENSE
Provides-Extra: testing
Dynamic: license-file
